<?xml version="1.0" encoding="ISO-8859-1"?><pnml>
    <net id="Net-One" type="P/T net">
        <labels x="669" y="286" width="110" height="28" border="true">
            <text>1*P5</text>
            <finalMarings>true</finalMarings>
        </labels>
        <place id="P0">
            <graphics>
                <position x="456.0" y="84.0"/>
            </graphics>
            <name>
                <value>P0</value>
                <graphics>
                    <offset x="-5.0" y="35.0"/>
                </graphics>
            </name>
            <msgPlace>false</msgPlace>
            <resPlace>false</resPlace>
            <linkPlace/>
            <dataPlace/>
            <initialMarking>
                <value>1</value>
                <graphics>
                    <offset x="0.0" y="0.0"/>
                </graphics>
            </initialMarking>
            <capacity>
                <value>0</value>
            </capacity>
        </place>
        <place id="P2">
            <graphics>
                <position x="312.0" y="264.0"/>
            </graphics>
            <name>
                <value>P2</value>
                <graphics>
                    <offset x="-5.0" y="35.0"/>
                </graphics>
            </name>
            <msgPlace>false</msgPlace>
            <resPlace>false</resPlace>
            <linkPlace/>
            <dataPlace/>
            <initialMarking>
                <value>0</value>
                <graphics>
                    <offset x="0.0" y="0.0"/>
                </graphics>
            </initialMarking>
            <capacity>
                <value>0</value>
            </capacity>
        </place>
        <place id="P5">
            <graphics>
                <position x="588.0" y="264.0"/>
            </graphics>
            <name>
                <value>P5</value>
                <graphics>
                    <offset x="13.0" y="35.0"/>
                </graphics>
            </name>
            <msgPlace>false</msgPlace>
            <resPlace>false</resPlace>
            <linkPlace/>
            <dataPlace/>
            <initialMarking>
                <value>0</value>
                <graphics>
                    <offset x="0.0" y="0.0"/>
                </graphics>
            </initialMarking>
            <capacity>
                <value>0</value>
            </capacity>
        </place>
        <transition id="T1">
            <graphics>
                <position x="456.0" y="168.0"/>
            </graphics>
            <name>
                <value>[0,starAmbulInst,{120 Command Center,Start Ambulance}]</value>
                <graphics>
                    <offset x="265.0" y="13.0"/>
                </graphics>
            </name>
            <routTran>false</routTran>
            <orientation>
                <value>0</value>
            </orientation>
            <rate>
                <value>1.0</value>
            </rate>
            <timed>
                <value>false</value>
            </timed>
            <minDelay>0.0</minDelay>
            <maxDelay>0.0</maxDelay>
            <infiniteServer>
                <value>false</value>
            </infiniteServer>
            <priority>
                <value>50</value>
            </priority>
        </transition>
        <transition id="T2">
            <graphics>
                <position x="456.0" y="264.0"/>
            </graphics>
            <name>
                <value>[0,follAmbulInst,{120 Command Center,Follow up Ambulance}]</value>
                <graphics>
                    <offset x="180.0" y="-9.0"/>
                </graphics>
            </name>
            <routTran>false</routTran>
            <orientation>
                <value>0</value>
            </orientation>
            <rate>
                <value>1.0</value>
            </rate>
            <timed>
                <value>false</value>
            </timed>
            <minDelay>0.0</minDelay>
            <maxDelay>0.0</maxDelay>
            <infiniteServer>
                <value>false</value>
            </infiniteServer>
            <priority>
                <value>50</value>
            </priority>
        </transition>
        <transition id="T4">
            <graphics>
                <position x="456.0" y="348.0"/>
            </graphics>
            <name>
                <value>NULL</value>
                <graphics>
                    <offset x="19.0" y="40.0"/>
                </graphics>
            </name>
            <routTran>false</routTran>
            <orientation>
                <value>0</value>
            </orientation>
            <rate>
                <value>1.0</value>
            </rate>
            <timed>
                <value>false</value>
            </timed>
            <minDelay>0.0</minDelay>
            <maxDelay>0.0</maxDelay>
            <infiniteServer>
                <value>false</value>
            </infiniteServer>
            <priority>
                <value>50</value>
            </priority>
        </transition>
        <arc id="P0 to T1" source="P0" target="T1">
            <graphics/>
            <inscription>
                <value>1</value>
                <graphics/>
            </inscription>
            <tagged>
                <value>false</value>
            </tagged>
            <arcpath id="000" x="465" y="104" curvePoint="false"/>
            <arcpath id="001" x="465" y="165" curvePoint="false"/>
            <type value="normal"/>
        </arc>
        <arc id="P2 to T2" source="P2" target="T2">
            <graphics/>
            <inscription>
                <value>1</value>
                <graphics/>
            </inscription>
            <tagged>
                <value>false</value>
            </tagged>
            <arcpath id="000" x="332" y="273" curvePoint="false"/>
            <arcpath id="001" x="460" y="273" curvePoint="false"/>
            <type value="normal"/>
        </arc>
        <arc id="P2 to T4" source="P2" target="T4">
            <graphics/>
            <inscription>
                <value>1</value>
                <graphics/>
            </inscription>
            <tagged>
                <value>false</value>
            </tagged>
            <arcpath id="000" x="331" y="279" curvePoint="false"/>
            <arcpath id="001" x="460" y="357" curvePoint="false"/>
            <type value="normal"/>
        </arc>
        <arc id="T1 to P2" source="T1" target="P2">
            <graphics/>
            <inscription>
                <value>1</value>
                <graphics/>
            </inscription>
            <tagged>
                <value>false</value>
            </tagged>
            <arcpath id="000" x="460" y="177" curvePoint="false"/>
            <arcpath id="001" x="330" y="266" curvePoint="false"/>
            <type value="normal"/>
        </arc>
        <arc id="T2 to P5" source="T2" target="P5">
            <graphics/>
            <inscription>
                <value>1</value>
                <graphics/>
            </inscription>
            <tagged>
                <value>false</value>
            </tagged>
            <arcpath id="000" x="468" y="273" curvePoint="false"/>
            <arcpath id="001" x="585" y="273" curvePoint="false"/>
            <type value="normal"/>
        </arc>
        <arc id="T4 to P5" source="T4" target="P5">
            <graphics/>
            <inscription>
                <value>1</value>
                <graphics/>
            </inscription>
            <tagged>
                <value>false</value>
            </tagged>
            <arcpath id="000" x="468" y="357" curvePoint="false"/>
            <arcpath id="001" x="586" y="279" curvePoint="false"/>
            <type value="normal"/>
        </arc>
    </net>
</pnml>
